object_storage_client.py
papai_minio.py
papai_public-0.1.7.dist-info/METADATA
papai_public-0.1.7.dist-info/WHEEL
papai_public-0.1.7.dist-info/top_level.txt
papai_public-0.1.7.dist-info/RECORD
