Metadata-Version: 2.1
Name: papai-public
Version: 0.1.7
Summary: Public papAI minio writer/reader
Author: Datategy
License: UNKNOWN
Platform: UNKNOWN
Requires-Dist: pyarrow
Requires-Dist: minio
Requires-Dist: loguru
Requires-Dist: azure-storage-blob
Requires-Dist: google-cloud-storage
